Metadata-Version: 1.1
Name: django-notification
Version: 1.3.3
Summary: User notification management for the Django web framework
Home-page: http://django-notification.rtfd.org/
Author: Pinax Developers
Author-email: developers@pinaxprojects.com
License: MIT
Platform: UNKNOWN
Classifier: Development Status :: 5 - Production/Stable
Classifier: Environment :: Web Environment
Classifier: Intended Audience :: Developers
Classifier: License :: OSI Approved :: MIT License
Classifier: Operating System :: OS Independent
Classifier: Programming Language :: Python :: 2.7
Classifier: Programming Language :: Python :: 3.3
Classifier: Framework :: Django
